odoo/addons/purchase_stock_picking_invoice_link/README.rst
odoo/addons/purchase_stock_picking_invoice_link/__init__.py
odoo/addons/purchase_stock_picking_invoice_link/__manifest__.py
odoo/addons/purchase_stock_picking_invoice_link/i18n/es.po
odoo/addons/purchase_stock_picking_invoice_link/i18n/purchase_stock_picking_invoice_link.pot
odoo/addons/purchase_stock_picking_invoice_link/models/__init__.py
odoo/addons/purchase_stock_picking_invoice_link/models/purchase_order.py
odoo/addons/purchase_stock_picking_invoice_link/models/stock_move.py
odoo/addons/purchase_stock_picking_invoice_link/readme/CONTRIBUTORS.rst
odoo/addons/purchase_stock_picking_invoice_link/readme/DESCRIPTION.rst
odoo/addons/purchase_stock_picking_invoice_link/readme/USAGE.rst
odoo/addons/purchase_stock_picking_invoice_link/static/description/icon.png
odoo/addons/purchase_stock_picking_invoice_link/static/description/index.html
odoo/addons/purchase_stock_picking_invoice_link/tests/__init__.py
odoo/addons/purchase_stock_picking_invoice_link/tests/test_purchase_stock_picking_invoice_link.py
odoo14_addon_purchase_stock_picking_invoice_link-14.0.1.1.0.dist-info/METADATA
odoo14_addon_purchase_stock_picking_invoice_link-14.0.1.1.0.dist-info/WHEEL
odoo14_addon_purchase_stock_picking_invoice_link-14.0.1.1.0.dist-info/top_level.txt
odoo14_addon_purchase_stock_picking_invoice_link-14.0.1.1.0.dist-info/RECORD
